collective.twittercards-0.1.3-py2.7-nspkg.pth
collective/twittercards/__init__.py
collective/twittercards/config.py
collective/twittercards/configure.zcml
collective/twittercards/interfaces.py
collective/twittercards/profiles.zcml
collective/twittercards/settings.py
collective/twittercards/setuphandlers.py
collective/twittercards/testing.py
collective/twittercards/vocabulary.py
collective/twittercards/Extensions/Install.py
collective/twittercards/Extensions/__init__.py
collective/twittercards/browser/__init__.py
collective/twittercards/browser/settings.py
collective/twittercards/browser/viewlets.py
collective/twittercards/browser/views.py
collective/twittercards/browser/templates/twittercardscontextpropertiesview.pt
collective/twittercards/browser/templates/twittercardsviewlet.pt
collective/twittercards/profiles/default/actions.xml
collective/twittercards/profiles/default/controlpanel.xml
collective/twittercards/profiles/default/import_steps.xml
collective/twittercards/profiles/default/metadata.xml
collective/twittercards/profiles/default/registry.xml
collective/twittercards/profiles/default/twittercards_install.txt
collective/twittercards/profiles/uninstall/import_steps.xml
collective/twittercards/profiles/uninstall/twittercards_uninstall.txt
collective/twittercards/tests/__init__.py
collective/twittercards/tests/test_controlpanel.py
collective.twittercards-0.1.3.dist-info/DESCRIPTION.rst
collective.twittercards-0.1.3.dist-info/METADATA
collective.twittercards-0.1.3.dist-info/RECORD
collective.twittercards-0.1.3.dist-info/WHEEL
collective.twittercards-0.1.3.dist-info/entry_points.txt
collective.twittercards-0.1.3.dist-info/metadata.json
collective.twittercards-0.1.3.dist-info/namespace_packages.txt
collective.twittercards-0.1.3.dist-info/paster_plugins.txt
collective.twittercards-0.1.3.dist-info/top_level.txt
