Metadata-Version: 2.0
Name: collective.twittercards
Version: 0.1.3
Summary: UNKNOWN
Home-page: https://github.com/collective/collective.twittercards
Author: Goldmund, Wyldebeast & Wunderliebe
Author-email: info@gw20e.com
License: GPL 2.0
Keywords: plone,twitter cards
Platform: UNKNOWN
Classifier: Environment :: Web Environment
Classifier: Framework :: Plone
Classifier: Operating System :: OS Independent
Classifier: Programming Language :: Python
Classifier: Programming Language :: Python :: 2.6
Classifier: Programming Language :: Python :: 2.7
Classifier: Topic :: Software Development :: Libraries :: Python Modules
Requires-Dist: setuptools
Requires-Dist: collective.z3cform.datagridfield
Requires-Dist: five.grok
Requires-Dist: plone.directives.form
Provides-Extra: test
Requires-Dist: plone.api; extra == 'test'
Requires-Dist: plone.app.testing[robot] (>=4.2.2); extra == 'test'
Requires-Dist: plone.testing; extra == 'test'
